penelope.py
penelope_shell_handler-0.15.0.dist-info/licenses/LICENSE
penelope_shell_handler-0.15.0.dist-info/METADATA
penelope_shell_handler-0.15.0.dist-info/WHEEL
penelope_shell_handler-0.15.0.dist-info/entry_points.txt
penelope_shell_handler-0.15.0.dist-info/top_level.txt
penelope_shell_handler-0.15.0.dist-info/RECORD
