Metadata-Version: 2.4
Name: penelope-shell-handler
Version: 0.15.0
Summary: Post-exploitation shell handler for authorized security testing
Author-email: brightio <brightio.code@gmail.com>
License: GPL-3.0-or-later
Project-URL: Homepage, https://github.com/brightio/penelope
Project-URL: Source, https://github.com/brightio/penelope
Project-URL: Issues, https://github.com/brightio/penelope/issues
Keywords: reverse-shell,tty,pty,rce,ctf,ctf-tools,oscp,shell-handler,hackthebox,oscp-tools,tryhackme
Classifier: Development Status :: 4 - Beta
Classifier: Intended Audience :: Information Technology
Classifier: Topic :: Security
Classifier: License :: OSI Approved :: GNU General Public License v3 or later (GPLv3+)
Classifier: Programming Language :: Python :: 3
Requires-Python: >=3.6
License-File: LICENSE
Dynamic: license-file
